[
  {
    "N": 5,
    "num_qubits": 4,
    "M_N": -2,
    "abs_M": 2,
    "total_edges": 3,
    "mean_degree": 1.5,
    "max_degree": 3,
    "cheapest_single_flip": 1,
    "avg_flip_cost_majority": 1.0,
    "leaf_nodes_in_majority": [
      "2=2",
      "3=3",
      "5=5"
    ],
    "paper_lc": 5.163562099482215,
    "corrected_lc": 5.163562099482215,
    "measured_lc": 5.1648533128104175,
    "f_predicted": 1.0,
    "ratio_vs_paper": 1.0002500625156288,
    "ratio_vs_corrected": 1.0002500625156288
  },
  {
    "N": 7,
    "num_qubits": 6,
    "M_N": -2,
    "abs_M": 2,
    "total_edges": 6,
    "mean_degree": 2.0,
    "max_degree": 4,
    "cheapest_single_flip": 1,
    "avg_flip_cost_majority": 1.5,
    "leaf_nodes_in_majority": [
      "5=5",
      "7=7"
    ],
    "paper_lc": 7.277798059018131,
    "corrected_lc": 7.277798059018131,
    "measured_lc": 7.279617963509009,
    "f_predicted": 1.0,
    "ratio_vs_paper": 1.000250062515629,
    "ratio_vs_corrected": 1.000250062515629
  },
  {
    "N": 8,
    "num_qubits": 6,
    "M_N": -2,
    "abs_M": 2,
    "total_edges": 6,
    "mean_degree": 2.0,
    "max_degree": 4,
    "cheapest_single_flip": 1,
    "avg_flip_cost_majority": 1.5,
    "leaf_nodes_in_majority": [
      "5=5",
      "7=7"
    ],
    "paper_lc": 8.339726086728971,
    "corrected_lc": 8.339726086728971,
    "measured_lc": 8.341811539613875,
    "f_predicted": 1.0,
    "ratio_vs_paper": 1.000250062515629,
    "ratio_vs_corrected": 1.000250062515629
  },
  {
    "N": 9,
    "num_qubits": 6,
    "M_N": -2,
    "abs_M": 2,
    "total_edges": 6,
    "mean_degree": 2.0,
    "max_degree": 4,
    "cheapest_single_flip": 1,
    "avg_flip_cost_majority": 1.5,
    "leaf_nodes_in_majority": [
      "5=5",
      "7=7"
    ],
    "paper_lc": 9.404319160296788,
    "corrected_lc": 9.404319160296788,
    "measured_lc": 9.40667082800379,
    "f_predicted": 1.0,
    "ratio_vs_paper": 1.000250062515629,
    "ratio_vs_corrected": 1.000250062515629
  },
  {
    "N": 11,
    "num_qubits": 8,
    "M_N": -2,
    "abs_M": 2,
    "total_edges": 9,
    "mean_degree": 2.25,
    "max_degree": 5,
    "cheapest_single_flip": 1,
    "avg_flip_cost_majority": 1.8,
    "leaf_nodes_in_majority": [
      "7=7",
      "11=11"
    ],
    "paper_lc": 11.540391410830134,
    "corrected_lc": 11.540391410830134,
    "measured_lc": 11.543277230137669,
    "f_predicted": 1.0,
    "ratio_vs_paper": 1.000250062515629,
    "ratio_vs_corrected": 1.000250062515629
  },
  {
    "N": 12,
    "num_qubits": 8,
    "M_N": -2,
    "abs_M": 2,
    "total_edges": 9,
    "mean_degree": 2.25,
    "max_degree": 5,
    "cheapest_single_flip": 1,
    "avg_flip_cost_majority": 1.8,
    "leaf_nodes_in_majority": [
      "7=7",
      "11=11"
    ],
    "paper_lc": 12.611445602550571,
    "corrected_lc": 12.611445602550571,
    "measured_lc": 12.614599252363663,
    "f_predicted": 1.0,
    "ratio_vs_paper": 1.000250062515629,
    "ratio_vs_corrected": 1.000250062515629
  },
  {
    "N": 13,
    "num_qubits": 9,
    "M_N": -3,
    "abs_M": 3,
    "total_edges": 10,
    "mean_degree": 2.2222222222222223,
    "max_degree": 6,
    "cheapest_single_flip": 1,
    "avg_flip_cost_majority": 1.6666666666666667,
    "leaf_nodes_in_majority": [
      "7=7",
      "11=11",
      "13=13"
    ],
    "paper_lc": 9.12285895165789,
    "corrected_lc": 6.842144213743417,
    "measured_lc": 6.843855177537801,
    "f_predicted": 0.75,
    "ratio_vs_paper": 0.7501875468867216,
    "ratio_vs_corrected": 1.0002500625156288
  },
  {
    "N": 14,
    "num_qubits": 10,
    "M_N": -2,
    "abs_M": 2,
    "total_edges": 12,
    "mean_degree": 2.4,
    "max_degree": 6,
    "cheapest_single_flip": 1,
    "avg_flip_cost_majority": 2.0,
    "leaf_nodes_in_majority": [
      "11=11",
      "13=13"
    ],
    "paper_lc": 14.758784667877816,
    "corrected_lc": 14.758784667877816,
    "measured_lc": 14.762475286699491,
    "f_predicted": 1.0,
    "ratio_vs_paper": 1.000250062515629,
    "ratio_vs_corrected": 1.000250062515629
  },
  {
    "N": 17,
    "num_qubits": 12,
    "M_N": -2,
    "abs_M": 2,
    "total_edges": 15,
    "mean_degree": 2.5,
    "max_degree": 7,
    "cheapest_single_flip": 1,
    "avg_flip_cost_majority": 2.142857142857143,
    "leaf_nodes_in_majority": [
      "11=11",
      "13=13",
      "17=17"
    ],
    "paper_lc": 17.991107552010178,
    "corrected_lc": 17.991107552010178,
    "measured_lc": 17.995606453623584,
    "f_predicted": 1.0,
    "ratio_vs_paper": 1.000250062515629,
    "ratio_vs_corrected": 1.000250062515629
  },
  {
    "N": 18,
    "num_qubits": 12,
    "M_N": -2,
    "abs_M": 2,
    "total_edges": 15,
    "mean_degree": 2.5,
    "max_degree": 7,
    "cheapest_single_flip": 1,
    "avg_flip_cost_majority": 2.142857142857143,
    "leaf_nodes_in_majority": [
      "11=11",
      "13=13",
      "17=17"
    ],
    "paper_lc": 19.071197127107872,
    "corrected_lc": 19.071197127107872,
    "measured_lc": 19.07596611863753,
    "f_predicted": 1.0,
    "ratio_vs_paper": 1.000250062515629,
    "ratio_vs_corrected": 1.000250062515629
  },
  {
    "N": 19,
    "num_qubits": 13,
    "M_N": -3,
    "abs_M": 3,
    "total_edges": 16,
    "mean_degree": 2.4615384615384617,
    "max_degree": 8,
    "cheapest_single_flip": 1,
    "avg_flip_cost_majority": 2.0,
    "leaf_nodes_in_majority": [
      "11=11",
      "13=13",
      "17=17",
      "19=19"
    ],
    "paper_lc": 13.43499205419606,
    "corrected_lc": 10.076244040647046,
    "measured_lc": 10.07876373157994,
    "f_predicted": 0.75,
    "ratio_vs_paper": 0.7501875468867216,
    "ratio_vs_corrected": 1.0002500625156288
  },
  {
    "N": 20,
    "num_qubits": 13,
    "M_N": -3,
    "abs_M": 3,
    "total_edges": 16,
    "mean_degree": 2.4615384615384617,
    "max_degree": 8,
    "cheapest_single_flip": 1,
    "avg_flip_cost_majority": 2.0,
    "leaf_nodes_in_majority": [
      "11=11",
      "13=13",
      "17=17",
      "19=19"
    ],
    "paper_lc": 14.156612238066382,
    "corrected_lc": 10.617459178549787,
    "measured_lc": 10.620114207101562,
    "f_predicted": 0.75,
    "ratio_vs_paper": 0.7501875468867217,
    "ratio_vs_corrected": 1.000250062515629
  },
  {
    "N": 21,
    "num_qubits": 14,
    "M_N": -2,
    "abs_M": 2,
    "total_edges": 18,
    "mean_degree": 2.5714285714285716,
    "max_degree": 8,
    "cheapest_single_flip": 1,
    "avg_flip_cost_majority": 2.25,
    "leaf_nodes_in_majority": [
      "11=11",
      "13=13",
      "17=17",
      "19=19"
    ],
    "paper_lc": 22.318432051969552,
    "corrected_lc": 22.318432051969552,
    "measured_lc": 22.324013055233358,
    "f_predicted": 1.0,
    "ratio_vs_paper": 1.0002500625156288,
    "ratio_vs_corrected": 1.0002500625156288
  },
  {
    "N": 23,
    "num_qubits": 16,
    "M_N": -2,
    "abs_M": 2,
    "total_edges": 21,
    "mean_degree": 2.625,
    "max_degree": 9,
    "cheapest_single_flip": 1,
    "avg_flip_cost_majority": 2.3333333333333335,
    "leaf_nodes_in_majority": [
      "13=13",
      "17=17",
      "19=19",
      "23=23"
    ],
    "paper_lc": 24.488511770377592,
    "corrected_lc": 24.488511770377592,
    "measured_lc": 24.4946354292349,
    "f_predicted": 1.0,
    "ratio_vs_paper": 1.000250062515629,
    "ratio_vs_corrected": 1.000250062515629
  },
  {
    "N": 24,
    "num_qubits": 16,
    "M_N": -2,
    "abs_M": 2,
    "total_edges": 21,
    "mean_degree": 2.625,
    "max_degree": 9,
    "cheapest_single_flip": 1,
    "avg_flip_cost_majority": 2.3333333333333335,
    "leaf_nodes_in_majority": [
      "13=13",
      "17=17",
      "19=19",
      "23=23"
    ],
    "paper_lc": 25.574989645124855,
    "corrected_lc": 25.574989645124855,
    "measured_lc": 25.581384991372698,
    "f_predicted": 1.0,
    "ratio_vs_paper": 1.000250062515629,
    "ratio_vs_corrected": 1.000250062515629
  },
  {
    "N": 25,
    "num_qubits": 16,
    "M_N": -2,
    "abs_M": 2,
    "total_edges": 21,
    "mean_degree": 2.625,
    "max_degree": 9,
    "cheapest_single_flip": 1,
    "avg_flip_cost_majority": 2.3333333333333335,
    "leaf_nodes_in_majority": [
      "13=13",
      "17=17",
      "19=19",
      "23=23"
    ],
    "paper_lc": 26.662373555209186,
    "corrected_lc": 26.662373555209186,
    "measured_lc": 26.66904081541304,
    "f_predicted": 1.0,
    "ratio_vs_paper": 1.000250062515629,
    "ratio_vs_corrected": 1.000250062515629
  },
  {
    "N": 29,
    "num_qubits": 18,
    "M_N": -2,
    "abs_M": 2,
    "total_edges": 24,
    "mean_degree": 2.6666666666666665,
    "max_degree": 10,
    "cheapest_single_flip": 1,
    "avg_flip_cost_majority": 2.4,
    "leaf_nodes_in_majority": [
      "17=17",
      "19=19",
      "23=23",
      "29=29"
    ],
    "paper_lc": 31.020297447174976,
    "corrected_lc": 31.020297447174976,
    "measured_lc": 31.028054460790173,
    "f_predicted": 1.0,
    "ratio_vs_paper": 1.000250062515629,
    "ratio_vs_corrected": 1.000250062515629
  },
  {
    "N": 30,
    "num_qubits": 19,
    "M_N": -3,
    "abs_M": 3,
    "total_edges": 27,
    "mean_degree": 2.8421052631578947,
    "max_degree": 10,
    "cheapest_single_flip": 1,
    "avg_flip_cost_majority": 2.4545454545454546,
    "leaf_nodes_in_majority": [
      "17=17",
      "19=19",
      "23=23",
      "29=29"
    ],
    "paper_lc": 21.407818830030838,
    "corrected_lc": 16.05586412252313,
    "measured_lc": 16.059879092296203,
    "f_predicted": 0.75,
    "ratio_vs_paper": 0.7501875468867217,
    "ratio_vs_corrected": 1.000250062515629
  },
  {
    "N": 31,
    "num_qubits": 20,
    "M_N": -4,
    "abs_M": 4,
    "total_edges": 28,
    "mean_degree": 2.8,
    "max_degree": 11,
    "cheapest_single_flip": 1,
    "avg_flip_cost_majority": 2.3333333333333335,
    "leaf_nodes_in_majority": [
      "17=17",
      "19=19",
      "23=23",
      "29=29",
      "31=31"
    ],
    "paper_lc": 16.601943519794233,
    "corrected_lc": 11.06796234652949,
    "measured_lc": 11.076265394051267,
    "f_predicted": 0.6666666666666666,
    "ratio_vs_paper": 0.6671667916979246,
    "ratio_vs_corrected": 1.0007501875468867
  },
  {
    "N": 32,
    "num_qubits": 20,
    "M_N": -4,
    "abs_M": 4,
    "total_edges": 28,
    "mean_degree": 2.8,
    "max_degree": 11,
    "cheapest_single_flip": 1,
    "avg_flip_cost_majority": 2.3333333333333335,
    "leaf_nodes_in_majority": [
      "17=17",
      "19=19",
      "23=23",
      "29=29",
      "31=31"
    ],
    "paper_lc": 17.14837540058069,
    "corrected_lc": 11.432250267053794,
    "measured_lc": 11.44082659883703,
    "f_predicted": 0.6666666666666666,
    "ratio_vs_paper": 0.6671667916979245,
    "ratio_vs_corrected": 1.0007501875468867
  },
  {
    "N": 33,
    "num_qubits": 21,
    "M_N": -3,
    "abs_M": 3,
    "total_edges": 30,
    "mean_degree": 2.857142857142857,
    "max_degree": 11,
    "cheapest_single_flip": 1,
    "avg_flip_cost_majority": 2.5,
    "leaf_nodes_in_majority": [
      "17=17",
      "19=19",
      "23=23",
      "29=29",
      "31=31"
    ],
    "paper_lc": 23.593531950834222,
    "corrected_lc": 17.695148963125668,
    "measured_lc": 17.699573856589815,
    "f_predicted": 0.75,
    "ratio_vs_paper": 0.7501875468867217,
    "ratio_vs_corrected": 1.000250062515629
  },
  {
    "N": 34,
    "num_qubits": 22,
    "M_N": -2,
    "abs_M": 2,
    "total_edges": 32,
    "mean_degree": 2.909090909090909,
    "max_degree": 11,
    "cheapest_single_flip": 1,
    "avg_flip_cost_majority": 2.6666666666666665,
    "leaf_nodes_in_majority": [
      "19=19",
      "23=23",
      "29=29",
      "31=31"
    ],
    "paper_lc": 36.48450810856541,
    "corrected_lc": 36.48450810856541,
    "measured_lc": 36.493631516444516,
    "f_predicted": 1.0,
    "ratio_vs_paper": 1.0002500625156288,
    "ratio_vs_corrected": 1.0002500625156288
  },
  {
    "N": 37,
    "num_qubits": 24,
    "M_N": -2,
    "abs_M": 2,
    "total_edges": 35,
    "mean_degree": 2.9166666666666665,
    "max_degree": 12,
    "cheapest_single_flip": 1,
    "avg_flip_cost_majority": 2.6923076923076925,
    "leaf_nodes_in_majority": [
      "19=19",
      "23=23",
      "29=29",
      "31=31",
      "37=37"
    ],
    "paper_lc": 39.77093109331375,
    "corrected_lc": 39.77093109331375,
    "measured_lc": 39.78087631239185,
    "f_predicted": 1.0,
    "ratio_vs_paper": 1.000250062515629,
    "ratio_vs_corrected": 1.000250062515629
  },
  {
    "N": 42,
    "num_qubits": 28,
    "M_N": -2,
    "abs_M": 2,
    "total_edges": 43,
    "mean_degree": 3.0714285714285716,
    "max_degree": 13,
    "cheapest_single_flip": 1,
    "avg_flip_cost_majority": 2.8666666666666667,
    "leaf_nodes_in_majority": [
      "23=23",
      "29=29",
      "31=31",
      "37=37",
      "41=41"
    ],
    "paper_lc": 45.259971506288316,
    "corrected_lc": 45.259971506288316,
    "measured_lc": null,
    "f_predicted": 1.0,
    "ratio_vs_paper": null,
    "ratio_vs_corrected": null
  },
  {
    "N": 43,
    "num_qubits": 29,
    "M_N": -3,
    "abs_M": 3,
    "total_edges": 44,
    "mean_degree": 3.0344827586206895,
    "max_degree": 14,
    "cheapest_single_flip": 1,
    "avg_flip_cost_majority": 2.75,
    "leaf_nodes_in_majority": [
      "23=23",
      "29=29",
      "31=31",
      "37=37",
      "41=41"
    ],
    "paper_lc": 30.906267958894116,
    "corrected_lc": 23.179700969170586,
    "measured_lc": null,
    "f_predicted": 0.75,
    "ratio_vs_paper": null,
    "ratio_vs_corrected": null
  },
  {
    "N": 44,
    "num_qubits": 29,
    "M_N": -3,
    "abs_M": 3,
    "total_edges": 44,
    "mean_degree": 3.0344827586206895,
    "max_degree": 14,
    "cheapest_single_flip": 1,
    "avg_flip_cost_majority": 2.75,
    "leaf_nodes_in_majority": [
      "23=23",
      "29=29",
      "31=31",
      "37=37",
      "41=41"
    ],
    "paper_lc": 31.639562598659655,
    "corrected_lc": 23.729671948994742,
    "measured_lc": null,
    "f_predicted": 0.75,
    "ratio_vs_paper": null,
    "ratio_vs_corrected": null
  },
  {
    "N": 45,
    "num_qubits": 29,
    "M_N": -3,
    "abs_M": 3,
    "total_edges": 44,
    "mean_degree": 3.0344827586206895,
    "max_degree": 14,
    "cheapest_single_flip": 1,
    "avg_flip_cost_majority": 2.75,
    "leaf_nodes_in_majority": [
      "23=23",
      "29=29",
      "31=31",
      "37=37",
      "41=41"
    ],
    "paper_lc": 32.37319065836194,
    "corrected_lc": 24.279892993771455,
    "measured_lc": null,
    "f_predicted": 0.75,
    "ratio_vs_paper": null,
    "ratio_vs_corrected": null
  },
  {
    "N": 46,
    "num_qubits": 30,
    "M_N": -2,
    "abs_M": 2,
    "total_edges": 46,
    "mean_degree": 3.066666666666667,
    "max_degree": 14,
    "cheapest_single_flip": 1,
    "avg_flip_cost_majority": 2.875,
    "leaf_nodes_in_majority": [
      "29=29",
      "31=31",
      "37=37",
      "41=41",
      "43=43"
    ],
    "paper_lc": 49.66071731104814,
    "corrected_lc": 49.66071731104814,
    "measured_lc": null,
    "f_predicted": 1.0,
    "ratio_vs_paper": null,
    "ratio_vs_corrected": null
  },
  {
    "N": 47,
    "num_qubits": 31,
    "M_N": -3,
    "abs_M": 3,
    "total_edges": 47,
    "mean_degree": 3.032258064516129,
    "max_degree": 15,
    "cheapest_single_flip": 1,
    "avg_flip_cost_majority": 2.764705882352941,
    "leaf_nodes_in_majority": [
      "29=29",
      "31=31",
      "37=37",
      "41=41",
      "43=43"
    ],
    "paper_lc": 33.84141829451158,
    "corrected_lc": 25.381063720883684,
    "measured_lc": null,
    "f_predicted": 0.75,
    "ratio_vs_paper": null,
    "ratio_vs_corrected": null
  },
  {
    "N": 48,
    "num_qubits": 31,
    "M_N": -3,
    "abs_M": 3,
    "total_edges": 47,
    "mean_degree": 3.032258064516129,
    "max_degree": 15,
    "cheapest_single_flip": 1,
    "avg_flip_cost_majority": 2.764705882352941,
    "leaf_nodes_in_majority": [
      "29=29",
      "31=31",
      "37=37",
      "41=41",
      "43=43"
    ],
    "paper_lc": 34.57600426160824,
    "corrected_lc": 25.93200319620618,
    "measured_lc": null,
    "f_predicted": 0.75,
    "ratio_vs_paper": null,
    "ratio_vs_corrected": null
  },
  {
    "N": 49,
    "num_qubits": 31,
    "M_N": -3,
    "abs_M": 3,
    "total_edges": 47,
    "mean_degree": 3.032258064516129,
    "max_degree": 15,
    "cheapest_single_flip": 1,
    "avg_flip_cost_majority": 2.764705882352941,
    "leaf_nodes_in_majority": [
      "29=29",
      "31=31",
      "37=37",
      "41=41",
      "43=43"
    ],
    "paper_lc": 35.310896391898716,
    "corrected_lc": 26.483172293924035,
    "measured_lc": null,
    "f_predicted": 0.75,
    "ratio_vs_paper": null,
    "ratio_vs_corrected": null
  },
  {
    "N": 50,
    "num_qubits": 31,
    "M_N": -3,
    "abs_M": 3,
    "total_edges": 47,
    "mean_degree": 3.032258064516129,
    "max_degree": 15,
    "cheapest_single_flip": 1,
    "avg_flip_cost_majority": 2.764705882352941,
    "leaf_nodes_in_majority": [
      "29=29",
      "31=31",
      "37=37",
      "41=41",
      "43=43"
    ],
    "paper_lc": 36.04608856000978,
    "corrected_lc": 27.034566420007334,
    "measured_lc": null,
    "f_predicted": 0.75,
    "ratio_vs_paper": null,
    "ratio_vs_corrected": null
  }
]